setup.cfg
setup.py
easingutilities/__init__.py
easingutilities.egg-info/PKG-INFO
easingutilities.egg-info/SOURCES.txt
easingutilities.egg-info/dependency_links.txt
easingutilities.egg-info/top_level.txt
easingutilities/easing/AbstractEase.py
easingutilities/easing/BackEase.py
easingutilities/easing/BackEaseIn.py
easingutilities/easing/BackEaseOut.py
easingutilities/easing/BadCircularBounceEase.py
easingutilities/easing/BounceEase.py
easingutilities/easing/BounceEaseIn.py
easingutilities/easing/BounceEaseOut.py
easingutilities/easing/CircularBounceEase.py
easingutilities/easing/CircularEase.py
easingutilities/easing/CircularEaseIn.py
easingutilities/easing/CircularEaseOut.py
easingutilities/easing/CubicEase.py
easingutilities/easing/ElasticEase.py
easingutilities/easing/ElasticEaseIn.py
easingutilities/easing/ElasticEaseOut.py
easingutilities/easing/ExponentialEase.py
easingutilities/easing/LinearEase.py
easingutilities/easing/QuadraticEase.py
easingutilities/easing/QuarticEase.py
easingutilities/easing/QuinticEase.py
easingutilities/easing/SinusoidalEase.py
easingutilities/easing/SinussoidalEaseIn.py
easingutilities/easing/SinussoidalEaseOut.py
easingutilities/easing/__init__.py
easingutilities/easingcontroller/EasingController.py
easingutilities/easingcontroller/__init__.py
easingutilities/exceptions/ControllerNotConfiguredException.py
easingutilities/exceptions/EasingException.py
easingutilities/exceptions/EasingNotConfiguredException.py
easingutilities/exceptions/WrongMovementException.py
easingutilities/exceptions/__init__.py