Metadata-Version: 1.1
Name: easingutilities
Version: 1.2
Summary: A controller for controlling Dynamixel motors with easing algorithms through pypot
Home-page: https://github.com/Robot-Boys/Easing-utilities
Author: Graunephar
Author-email: daniel@graungaard.com
License: UNKNOWN
Download-URL: https://github.com/Robot-Boys/Easing-utilities/archive/1.2.tar.gz
Keywords: Dynamixel,Easing,Motor
Platform: UNKNOWN
Classifier: Development Status :: 3 - Alpha
Classifier: Intended Audience :: Developers
Classifier: Topic :: Software Development :: Build Tools
Classifier: License :: OSI Approved :: MIT License
Classifier: Programming Language :: Python :: 3.4
